README.txt
setup.py
collective/__init__.py
collective.js.blackbird.egg-info/PKG-INFO
collective.js.blackbird.egg-info/SOURCES.txt
collective.js.blackbird.egg-info/dependency_links.txt
collective.js.blackbird.egg-info/entry_points.txt
collective.js.blackbird.egg-info/namespace_packages.txt
collective.js.blackbird.egg-info/not-zip-safe
collective.js.blackbird.egg-info/requires.txt
collective.js.blackbird.egg-info/top_level.txt
collective/js/__init__.py
collective/js/blackbird/__init__.py
collective/js/blackbird/configure.zcml
collective/js/blackbird/interfaces.py
collective/js/blackbird/browser/__init__.py
collective/js/blackbird/browser/blackbird.css
collective/js/blackbird/browser/blackbird.js
collective/js/blackbird/browser/blackbird_disabled.js
collective/js/blackbird/browser/configure.zcml
collective/js/blackbird/browser/toggle.pt
collective/js/blackbird/browser/viewlets.py
collective/js/blackbird/profiles/default/browserlayer.xml
collective/js/blackbird/profiles/default/cssregistry.xml
collective/js/blackbird/profiles/default/jsregistry.xml
collective/js/blackbird/profiles/default/metadata.xml
collective/js/blackbird/profiles/default/skins.xml
collective/js/blackbird/skins/blackbird_images/blackbird_icons.png
collective/js/blackbird/skins/blackbird_images/blackbird_panel.png
docs/HISTORY.txt