Metadata-Version: 1.0
Name: collective.js.blackbird
Version: 1.2.1
Summary: A Plone add-on package that provides Blackbird.js, an Open-Source Javascript logging utility.
Home-page: http://www.gscottolson.com/blackbirdjs/
Author: JC Brand for Syslab.com GmbH, Blackbird.js by G. Scott Olson
Author-email: brand@syslab.com
License: GPL
Keywords: javascript logging plone blackbird
Platform: UNKNOWN
Classifier: Programming Language :: Python
